claun/__init__.py
claun/__main__.py
claun/cli.py
claun/core/__init__.py
claun/core/config.py
claun/core/executor.py
claun/core/scheduler.py
claun/headless/__init__.py
claun/headless/runner.py
claun/logging/__init__.py
claun/logging/manager.py
claun/scheduling/__init__.py
claun/scheduling/calculator.py
claun/scheduling/models.py
claun/tui/__init__.py
claun/tui/app.py
claun/tui/screens/__init__.py
claun/tui/screens/save_config.py
claun/tui/widgets/__init__.py
claun_tui-0.3.0.dist-info/METADATA
claun_tui-0.3.0.dist-info/WHEEL
claun_tui-0.3.0.dist-info/entry_points.txt
claun_tui-0.3.0.dist-info/licenses/LICENSE
claun_tui-0.3.0.dist-info/RECORD
