Metadata-Version: 2.4
Name: claun-tui
Version: 0.3.0
Summary: Schedule Claude Code jobs with a beautiful TUI or headless mode
Project-URL: Homepage, https://github.com/nsmith/claun
Project-URL: Repository, https://github.com/nsmith/claun
Project-URL: Issues, https://github.com/nsmith/claun/issues
Author: nsmith
License: GPL-3.0
License-File: LICENSE
Keywords: automation,claude,cli,scheduler,tui
Classifier: Development Status :: 3 - Alpha
Classifier: Environment :: Console
Classifier: Intended Audience :: Developers
Classifier: License :: OSI Approved :: GNU General Public License v3 (GPLv3)
Classifier: Operating System :: OS Independent
Classifier: Programming Language :: Python :: 3
Classifier: Programming Language :: Python :: 3.10
Classifier: Programming Language :: Python :: 3.11
Classifier: Programming Language :: Python :: 3.12
Classifier: Programming Language :: Python :: 3.13
Classifier: Topic :: Software Development :: Libraries :: Python Modules
Classifier: Topic :: Utilities
Requires-Python: >=3.10
Requires-Dist: croniter>=2.0.0
Requires-Dist: rich>=13.0.0
Requires-Dist: textual>=0.89.0
Requires-Dist: typer>=0.12.0
Provides-Extra: dev
Requires-Dist: mypy>=1.8.0; extra == 'dev'
Requires-Dist: pre-commit>=3.0.0; extra == 'dev'
Requires-Dist: pytest-asyncio>=0.23.0; extra == 'dev'
Requires-Dist: pytest-cov>=4.0.0; extra == 'dev'
Requires-Dist: pytest>=8.0.0; extra == 'dev'
Requires-Dist: ruff>=0.4.0; extra == 'dev'
Requires-Dist: textual-dev>=1.0.0; extra == 'dev'
